snowfakery_mcp/bundled_docs/__init__.py
snowfakery_mcp/bundled_docs/extending.md
snowfakery_mcp/bundled_docs/index.md
snowfakery_mcp/bundled_docs/salesforce.md
snowfakery_mcp/bundled_docs/arch/ArchIndex.md
snowfakery_mcp/bundled_docs/arch/__init__.py
snowfakery_mcp/bundled_examples/__init__.py
snowfakery_mcp/bundled_examples/bad_soql_dataset.recipe.yml
snowfakery_mcp/bundled_examples/base64_file.recipe.yml
snowfakery_mcp/bundled_examples/basic-salesforce.recipe.yml
snowfakery_mcp/bundled_examples/binary.recipe.yml
snowfakery_mcp/bundled_examples/company.yml
snowfakery_mcp/bundled_examples/company2.yml
snowfakery_mcp/bundled_examples/company3.yml
snowfakery_mcp/bundled_examples/conditional.yml
snowfakery_mcp/bundled_examples/count_up_plugin.yml
snowfakery_mcp/bundled_examples/datetime_with_params.recipe.yml
snowfakery_mcp/bundled_examples/deep_references.yml
snowfakery_mcp/bundled_examples/faker_in_formula.recipe.yml
snowfakery_mcp/bundled_examples/family.recipe.yml
snowfakery_mcp/bundled_examples/hidden_fields.yml
snowfakery_mcp/bundled_examples/jinja_filters.recipe.yml
snowfakery_mcp/bundled_examples/lastname_var.yml
snowfakery_mcp/bundled_examples/math.yml
snowfakery_mcp/bundled_examples/native_types_differences.yml
snowfakery_mcp/bundled_examples/nested_macros.recipe.yml
snowfakery_mcp/bundled_examples/null.yml
snowfakery_mcp/bundled_examples/parameters.recipe.yml
snowfakery_mcp/bundled_examples/parameters_block.recipe.yml
snowfakery_mcp/bundled_examples/price_math.recipe.yml
snowfakery_mcp/bundled_examples/random-choice-complex.yml
snowfakery_mcp/bundled_examples/random-reference-stress-test.yml
snowfakery_mcp/bundled_examples/random-reference.yml
snowfakery_mcp/bundled_examples/salesforce_soql_example.recipe.yml
snowfakery_mcp/bundled_examples/salesforce_soql_example_no_records.recipe.yml
snowfakery_mcp/bundled_examples/simple_datetime.recipe.yml
snowfakery_mcp/bundled_examples/soql_dataset.recipe.yml
snowfakery_mcp-0.0.5.dist-info/METADATA
snowfakery_mcp-0.0.5.dist-info/WHEEL
snowfakery_mcp-0.0.5.dist-info/entry_points.txt
snowfakery_mcp-0.0.5.dist-info/licenses/LICENSE-APACHE
snowfakery_mcp-0.0.5.dist-info/licenses/LICENSE-MIT
snowfakery_mcp-0.0.5.dist-info/RECORD
