Metadata-Version: 2.4
Name: snowfakery-mcp
Version: 0.0.5
Summary: MCP server for authoring, analyzing, debugging, and running Snowfakery recipes
License-File: LICENSE-APACHE
License-File: LICENSE-MIT
Requires-Python: >=3.12
Requires-Dist: fastmcp>=2.14.3
Requires-Dist: openai>=2.15.0
Requires-Dist: snowfakery>=4.2.1
